mojo/landscaping/__init__.py
mojo/landscaping/agents/__init__.py
mojo/landscaping/agents/localcommandagent.py
mojo/landscaping/agents/poweragentbase.py
mojo/landscaping/agents/serialagentbase.py
mojo/landscaping/agents/systemagentbase.py
mojo/landscaping/automationpod.py
mojo/landscaping/client/__init__.py
mojo/landscaping/client/clientbase.py
mojo/landscaping/client/clientcoordinatorbase.py
mojo/landscaping/client/clientcoordinatorcouplingbase.py
mojo/landscaping/cluster/__init__.py
mojo/landscaping/cluster/nodebase.py
mojo/landscaping/cluster/nodecoordinatorbase.py
mojo/landscaping/cluster/nodecoordinatorcouplingbase.py
mojo/landscaping/configurationextractor.py
mojo/landscaping/constants.py
mojo/landscaping/coordinators/__init__.py
mojo/landscaping/coordinators/coordinatorbase.py
mojo/landscaping/coupling/__init__.py
mojo/landscaping/coupling/coordinatorcoupling.py
mojo/landscaping/friendlyidentifier.py
mojo/landscaping/includefilters.py
mojo/landscaping/landscape.py
mojo/landscaping/landscapedevice.py
mojo/landscaping/landscapedevicecluster.py
mojo/landscaping/landscapedevicegroup.py
mojo/landscaping/landscapeparameters.py
mojo/landscaping/landscapeservice.py
mojo/landscaping/landscapingextensionprotocol.py
mojo/landscaping/layers/landscapeconfigurationlayer.py
mojo/landscaping/layers/landscapeinstallationlayer.py
mojo/landscaping/layers/landscapeintegrationlayer.py
mojo/landscaping/layers/landscapeoperationallayer.py
mojo/landscaping/layers/landscapinglayerbase.py
mojo/landscaping/layers/topologyintegrationlayer.py
mojo/landscaping/protocolextension.py
mojo/landscaping/service/__init__.py
mojo/landscaping/service/servicebase.py
mojo/landscaping/service/servicecoordinatorbase.py
mojo/landscaping/service/servicecoordinatorcouplingbase.py
mojo/landscaping/wellknown.py
mojo_landscaping-2.0.4.dist-info/LICENSE.txt
mojo_landscaping-2.0.4.dist-info/METADATA
mojo_landscaping-2.0.4.dist-info/WHEEL
mojo_landscaping-2.0.4.dist-info/RECORD
