Metadata-Version: 2.1
Name: mojo-landscaping
Version: 2.0.4
Summary: Automation Mojo Landscaping Package
License: LICENSE.txt
Keywords: python
Author: Myron W Walker
Requires-Python: >=3.9,<4.0
Classifier: License :: OSI Approved :: MIT License
Classifier: License :: Other/Proprietary License
Classifier: Operating System :: POSIX
Classifier: Programming Language :: Python :: 3
Classifier: Programming Language :: Python :: 3.9
Classifier: Programming Language :: Python :: 3.10
Classifier: Programming Language :: Python :: 3.11
Classifier: Programming Language :: Python :: 3.12
Requires-Dist: mojo-config (>=2.0.0,<2.1.0)
Requires-Dist: mojo-credentials (>=2.0.0,<2.1.0)
Requires-Dist: mojo-extension (>=2.0.0,<2.1.0)
Requires-Dist: mojo-interfaces (>=2.0.0,<2.1.0)
Requires-Dist: mojo-xmodules (>=2.0.0,<2.1.0)
